google/cloud/discoveryengine/__init__.py
google/cloud/discoveryengine/gapic_version.py
google/cloud/discoveryengine/py.typed
google/cloud/discoveryengine_v1/__init__.py
google/cloud/discoveryengine_v1/gapic_metadata.json
google/cloud/discoveryengine_v1/gapic_version.py
google/cloud/discoveryengine_v1/py.typed
google/cloud/discoveryengine_v1/services/__init__.py
google/cloud/discoveryengine_v1/services/assistant_service/__init__.py
google/cloud/discoveryengine_v1/services/assistant_service/async_client.py
google/cloud/discoveryengine_v1/services/assistant_service/client.py
google/cloud/discoveryengine_v1/services/assistant_service/transports/__init__.py
google/cloud/discoveryengine_v1/services/assistant_service/transports/base.py
google/cloud/discoveryengine_v1/services/assistant_service/transports/grpc.py
google/cloud/discoveryengine_v1/services/assistant_service/transports/grpc_asyncio.py
google/cloud/discoveryengine_v1/services/assistant_service/transports/rest.py
google/cloud/discoveryengine_v1/services/assistant_service/transports/rest_base.py
google/cloud/discoveryengine_v1/services/cmek_config_service/__init__.py
google/cloud/discoveryengine_v1/services/cmek_config_service/async_client.py
google/cloud/discoveryengine_v1/services/cmek_config_service/client.py
google/cloud/discoveryengine_v1/services/cmek_config_service/transports/__init__.py
google/cloud/discoveryengine_v1/services/cmek_config_service/transports/base.py
google/cloud/discoveryengine_v1/services/cmek_config_service/transports/grpc.py
google/cloud/discoveryengine_v1/services/cmek_config_service/transports/grpc_asyncio.py
google/cloud/discoveryengine_v1/services/cmek_config_service/transports/rest.py
google/cloud/discoveryengine_v1/services/cmek_config_service/transports/rest_base.py
google/cloud/discoveryengine_v1/services/completion_service/__init__.py
google/cloud/discoveryengine_v1/services/completion_service/async_client.py
google/cloud/discoveryengine_v1/services/completion_service/client.py
google_cloud_discoveryengine-0.15.0.dist-info/licenses/LICENSE
google_cloud_discoveryengine-0.15.0.dist-info/METADATA
google_cloud_discoveryengine-0.15.0.dist-info/WHEEL
google_cloud_discoveryengine-0.15.0.dist-info/top_level.txt
google_cloud_discoveryengine-0.15.0.dist-info/RECORD
